LICENSE
MANIFEST.in
README.md
README.rst
setup.py
imageGrid/__init__.py
imageGrid/imageGrid.py
imageGrid.egg-info/PKG-INFO
imageGrid.egg-info/SOURCES.txt
imageGrid.egg-info/dependency_links.txt
imageGrid.egg-info/not-zip-safe
imageGrid.egg-info/requires.txt
imageGrid.egg-info/top_level.txt