Metadata-Version: 1.0
Name: imageGrid
Version: 0.1.0
Summary: Split an image into grid
Home-page: https://github.com/wwwins/ImageGridPython
Author: wwwins
Author-email: cphuang72@gmail.com
License: MIT
Keywords: imageGrid instagram grid
Platform: UNKNOWN
